kafka_avro_binary_consumer/__init__.py
kafka_avro_binary_consumer/binary_avro_consumer.py
kafka_avro_binary_consumer-0.0.0.2.dist-info/LICENSE
kafka_avro_binary_consumer-0.0.0.2.dist-info/METADATA
kafka_avro_binary_consumer-0.0.0.2.dist-info/WHEEL
kafka_avro_binary_consumer-0.0.0.2.dist-info/top_level.txt
kafka_avro_binary_consumer-0.0.0.2.dist-info/RECORD
