Metadata-Version: 2.1
Name: kafka-avro-binary-consumer
Version: 0.0.0.2
Summary: Kafka avro binary consumer with postgres config
Home-page: https://example.com
Author: Tarasenko Stepan
Author-email: st.a.tarasenko@gmail.com
License: UNKNOWN
Platform: UNKNOWN
Classifier: Programming Language :: Python :: 3
Classifier: License :: OSI Approved :: MIT License
Classifier: Operating System :: OS Independent
